{
  "hash": "a5bf1d47",
  "configHash": "ae6afaa4",
  "lockfileHash": "1b4296cf",
  "browserHash": "c376ca12",
  "optimized": {
    "react": {
      "src": "../../node_modules/react/index.js",
      "file": "react.js",
      "fileHash": "62159191",
      "needsInterop": true
    },
    "react-dom": {
      "src": "../../node_modules/react-dom/index.js",
      "file": "react-dom.js",
      "fileHash": "7750f8f0",
      "needsInterop": true
    },
    "react/jsx-dev-runtime": {
      "src": "../../node_modules/react/jsx-dev-runtime.js",
      "file": "react_jsx-dev-runtime.js",
      "fileHash": "85ef5860",
      "needsInterop": true
    },
    "react/jsx-runtime": {
      "src": "../../node_modules/react/jsx-runtime.js",
      "file": "react_jsx-runtime.js",
      "fileHash": "76125602",
      "needsInterop": true
    },
    "clsx": {
      "src": "../../node_modules/clsx/dist/clsx.mjs",
      "file": "clsx.js",
      "fileHash": "1a118e59",
      "needsInterop": false
    },
    "lucide-react": {
      "src": "../../node_modules/lucide-react/dist/esm/lucide-react.js",
      "file": "lucide-react.js",
      "fileHash": "5551df91",
      "needsInterop": false
    },
    "react-dom/client": {
      "src": "../../node_modules/react-dom/client.js",
      "file": "react-dom_client.js",
      "fileHash": "494e1566",
      "needsInterop": true
    },
    "tailwind-merge": {
      "src": "../../node_modules/tailwind-merge/dist/bundle-mjs.mjs",
      "file": "tailwind-merge.js",
      "fileHash": "b4a7bbb2",
      "needsInterop": false
    },
    "zustand": {
      "src": "../../node_modules/zustand/esm/index.mjs",
      "file": "zustand.js",
      "fileHash": "5ab2cff9",
      "needsInterop": false
    }
  },
  "chunks": {
    "chunk-7I2UKMSJ": {
      "file": "chunk-7I2UKMSJ.js"
    },
    "chunk-P6RTVJOB": {
      "file": "chunk-P6RTVJOB.js"
    },
    "chunk-G3PMV62Z": {
      "file": "chunk-G3PMV62Z.js"
    }
  }
}